prism_sdk/__init__.py
prism_sdk/client.py
prism_sdk/models.py
prism_sdk/taas_client.py
prism_sdk/taas_models.py
prism_sdk-1.1.0.dist-info/licenses/LICENSE
prism_sdk-1.1.0.dist-info/METADATA
prism_sdk-1.1.0.dist-info/WHEEL
prism_sdk-1.1.0.dist-info/top_level.txt
prism_sdk-1.1.0.dist-info/RECORD
