Metadata-Version: 2.4
Name: prism-sdk
Version: 1.1.0
Summary: Official Python SDK for Prism Meta - AI-Powered Trust Verification API
Home-page: https://github.com/prismmeta/prism-sdk-python
Author: Prism Labs
Author-email: Prism Meta <support@prismmeta.com>
Maintainer-email: Prism Meta <support@prismmeta.com>
License-Expression: MIT
Project-URL: Homepage, https://github.com/prismmeta/prism-sdk-python
Project-URL: Documentation, https://docs.prismmeta.ai/sdk/python
Project-URL: Repository, https://github.com/prismmeta/prism-sdk-python
Project-URL: Bug Tracker, https://github.com/prismmeta/prism-sdk-python/issues
Project-URL: API Reference, https://api.prismmeta.ai/docs
Keywords: prism,trust,verification,fact-checking,ai,api,sdk
Classifier: Development Status :: 5 - Production/Stable
Classifier: Intended Audience :: Developers
Classifier: Operating System :: OS Independent
Classifier: Programming Language :: Python :: 3
Classifier: Programming Language :: Python :: 3.8
Classifier: Programming Language :: Python :: 3.9
Classifier: Programming Language :: Python :: 3.10
Classifier: Programming Language :: Python :: 3.11
Classifier: Programming Language :: Python :: 3.12
Classifier: Topic :: Software Development :: Libraries :: Python Modules
Classifier: Topic :: Internet :: WWW/HTTP :: Dynamic Content
Classifier: Topic :: Scientific/Engineering :: Artificial Intelligence
Requires-Python: >=3.8
License-File: LICENSE
Requires-Dist: httpx>=0.25.0
Requires-Dist: pydantic>=2.0.0
Provides-Extra: dev
Requires-Dist: pytest>=7.0.0; extra == "dev"
Requires-Dist: pytest-asyncio>=0.20.0; extra == "dev"
Requires-Dist: black>=22.0.0; extra == "dev"
Requires-Dist: isort>=5.0.0; extra == "dev"
Requires-Dist: mypy>=1.0.0; extra == "dev"
Requires-Dist: flake8>=5.0.0; extra == "dev"
Provides-Extra: docs
Requires-Dist: mkdocs>=1.4.0; extra == "docs"
Requires-Dist: mkdocs-material>=8.0.0; extra == "docs"
Requires-Dist: mkdocstrings[python]>=0.19.0; extra == "docs"
Dynamic: author
Dynamic: home-page
Dynamic: license-file
Dynamic: requires-python
